{
  "elements": [
    {
      "element": {
        "element_type": "minecraft:single_pool_element",
        "location": "trailiertales:catacombs/room/art_studio",
        "processors": "trailiertales:catacombs_small_room",
        "projection": "rigid"
      },
      "weight": 10
    },
    {
      "element": {
        "element_type": "minecraft:single_pool_element",
        "location": "trailiertales:catacombs/room/buried1",
        "processors": "trailiertales:catacombs_small_room",
        "projection": "rigid"
      },
      "weight": 10
    },
    {
      "element": {
        "element_type": "minecraft:single_pool_element",
        "location": "trailiertales:catacombs/room/buried2",
        "processors": "trailiertales:catacombs_small_room",
        "projection": "rigid"
      },
      "weight": 10
    },
    {
      "element": {
        "element_type": "minecraft:single_pool_element",
        "location": "trailiertales:catacombs/room/cabin1",
        "processors": "trailiertales:catacombs_small_room",
        "projection": "rigid"
      },
      "weight": 10
    },
    {
      "element": {
        "element_type": "minecraft:single_pool_element",
        "location": "trailiertales:catacombs/room/cabin2",
        "processors": "trailiertales:catacombs_small_room",
        "projection": "rigid"
      },
      "weight": 10
    },
    {
      "element": {
        "element_type": "minecraft:single_pool_element",
        "location": "trailiertales:catacombs/room/generic1",
        "processors": "trailiertales:catacombs_small_room",
        "projection": "rigid"
      },
      "weight": 10
    },
    {
      "element": {
        "element_type": "minecraft:single_pool_element",
        "location": "trailiertales:catacombs/room/generic2",
        "processors": "trailiertales:catacombs_small_room",
        "projection": "rigid"
      },
      "weight": 10
    },
    {
      "element": {
        "element_type": "minecraft:single_pool_element",
        "location": "trailiertales:catacombs/room/generic3",
        "processors": "trailiertales:catacombs_small_room",
        "projection": "rigid"
      },
      "weight": 10
    },
    {
      "element": {
        "element_type": "minecraft:single_pool_element",
        "location": "trailiertales:catacombs/room/generic4",
        "processors": "trailiertales:catacombs_small_room",
        "projection": "rigid"
      },
      "weight": 10
    },
    {
      "element": {
        "element_type": "minecraft:single_pool_element",
        "location": "trailiertales:catacombs/room/generic5",
        "processors": "trailiertales:catacombs_small_room",
        "projection": "rigid"
      },
      "weight": 10
    },
    {
      "element": {
        "element_type": "minecraft:single_pool_element",
        "location": "trailiertales:catacombs/room/generic6",
        "processors": "trailiertales:catacombs_small_room",
        "projection": "rigid"
      },
      "weight": 10
    },
    {
      "element": {
        "element_type": "minecraft:single_pool_element",
        "location": "trailiertales:catacombs/room/generic7",
        "processors": "trailiertales:catacombs_small_room",
        "projection": "rigid"
      },
      "weight": 10
    },
    {
      "element": {
        "element_type": "minecraft:single_pool_element",
        "location": "trailiertales:catacombs/room/generic8",
        "processors": "trailiertales:catacombs_small_room",
        "projection": "rigid"
      },
      "weight": 10
    },
    {
      "element": {
        "element_type": "minecraft:single_pool_element",
        "location": "trailiertales:catacombs/room/generic9",
        "processors": "trailiertales:catacombs_small_room",
        "projection": "rigid"
      },
      "weight": 10
    },
    {
      "element": {
        "element_type": "minecraft:single_pool_element",
        "location": "trailiertales:catacombs/room/generic10",
        "processors": "trailiertales:catacombs_small_room",
        "projection": "rigid"
      },
      "weight": 10
    },
    {
      "element": {
        "element_type": "minecraft:single_pool_element",
        "location": "trailiertales:catacombs/room/generic11",
        "processors": "trailiertales:catacombs_small_room",
        "projection": "rigid"
      },
      "weight": 10
    },
    {
      "element": {
        "element_type": "minecraft:single_pool_element",
        "location": "trailiertales:catacombs/room/generic12",
        "processors": "trailiertales:catacombs_small_room",
        "projection": "rigid"
      },
      "weight": 10
    },
    {
      "element": {
        "element_type": "minecraft:single_pool_element",
        "location": "trailiertales:catacombs/room/generic13",
        "processors": "trailiertales:catacombs_small_room",
        "projection": "rigid"
      },
      "weight": 10
    },
    {
      "element": {
        "element_type": "minecraft:single_pool_element",
        "location": "trailiertales:catacombs/room/jail",
        "processors": "trailiertales:catacombs_small_room",
        "projection": "rigid"
      },
      "weight": 10
    },
    {
      "element": {
        "element_type": "minecraft:single_pool_element",
        "location": "trailiertales:catacombs/room/kitchen",
        "processors": "trailiertales:catacombs_small_room",
        "projection": "rigid"
      },
      "weight": 10
    },
    {
      "element": {
        "element_type": "minecraft:single_pool_element",
        "location": "trailiertales:catacombs/room/mine1",
        "processors": "trailiertales:catacombs_small_room",
        "projection": "rigid"
      },
      "weight": 10
    },
    {
      "element": {
        "element_type": "minecraft:single_pool_element",
        "location": "trailiertales:catacombs/room/mine2",
        "processors": "trailiertales:catacombs_small_room",
        "projection": "rigid"
      },
      "weight": 10
    },
    {
      "element": {
        "element_type": "minecraft:single_pool_element",
        "location": "trailiertales:catacombs/room/portal",
        "processors": "trailiertales:catacombs_small_room",
        "projection": "rigid"
      },
      "weight": 10
    },
    {
      "element": {
        "element_type": "minecraft:single_pool_element",
        "location": "trailiertales:catacombs/room/pot_making",
        "processors": "trailiertales:catacombs_small_room",
        "projection": "rigid"
      },
      "weight": 10
    },
    {
      "element": {
        "element_type": "minecraft:single_pool_element",
        "location": "trailiertales:catacombs/room/ritual1",
        "processors": "trailiertales:catacombs_small_room",
        "projection": "rigid"
      },
      "weight": 10
    },
    {
      "element": {
        "element_type": "minecraft:single_pool_element",
        "location": "trailiertales:catacombs/room/ritual2",
        "processors": "trailiertales:catacombs_small_room",
        "projection": "rigid"
      },
      "weight": 10
    },
    {
      "element": {
        "element_type": "minecraft:single_pool_element",
        "location": "trailiertales:catacombs/room/ritual3",
        "processors": "trailiertales:catacombs_small_room",
        "projection": "rigid"
      },
      "weight": 10
    },
    {
      "element": {
        "element_type": "minecraft:single_pool_element",
        "location": "trailiertales:catacombs/room/ritual4",
        "processors": "trailiertales:catacombs_small_room",
        "projection": "rigid"
      },
      "weight": 10
    },
    {
      "element": {
        "element_type": "minecraft:single_pool_element",
        "location": "trailiertales:catacombs/room/ritual5",
        "processors": "trailiertales:catacombs_small_room",
        "projection": "rigid"
      },
      "weight": 10
    },
    {
      "element": {
        "element_type": "minecraft:single_pool_element",
        "location": "trailiertales:catacombs/room/ritual6",
        "processors": "trailiertales:catacombs_small_room",
        "projection": "rigid"
      },
      "weight": 10
    },
    {
      "element": {
        "element_type": "minecraft:single_pool_element",
        "location": "trailiertales:catacombs/room/storage",
        "processors": "trailiertales:catacombs_small_room",
        "projection": "rigid"
      },
      "weight": 10
    }
  ],
  "fallback": "minecraft:empty"
}