{
  "parent": "minecraft:recipes/root",
  "criteria": {
    "has_pale_hanging_moss": {
      "conditions": {
        "items": [
          {
            "items": "minecraft:pale_hanging_moss"
          }
        ]
      },
      "trigger": "minecraft:inventory_changed"
    },
    "has_the_recipe": {
      "conditions": {
        "recipe": "minecraft:pale_mossy_resin_bricks_from_pale_hanging_moss"
      },
      "trigger": "minecraft:recipe_unlocked"
    }
  },
  "requirements": [
    [
      "has_the_recipe",
      "has_pale_hanging_moss"
    ]
  ],
  "rewards": {
    "recipes": [
      "minecraft:pale_mossy_resin_bricks_from_pale_hanging_moss"
    ]
  }
}